[{
  "_id": {
    "$oid": "66c8e3983b9fd081fe7cc8e3"
  },
  "titulo": "Alien Romulus",
  "genero": [
    "Sci-Fi",
    "Horror"
  ],
  "duracion": 120,
  "sinopsis": "En un planeta lejano, un grupo de colonos se enfrenta a una nueva amenaza alienígena que podría poner en peligro la supervivencia de la humanidad.",
  "img": "https://posters.movieposterdb.com/24_03/2024/18412256/l_alien-romulus-movie-poster_740eb569.jpg",
  "casting": [
    {
      "img": "https://images.movieposterdb.com/profile_images/5097044/t_34045611_isabela-merced.jpg",
      "nombre": "Isabela Mercad",
      "personaje": "Juni"
    },
    {
      "img": "https://images.movieposterdb.com/profile_images/8314228/t_fa8bfc09_cailee-spaeny.jpg",
      "nombre": "Cailee Spaeny",
      "personaje": "Carla"
    },
    {
      "img": "https://images.movieposterdb.com/profile_images/8850556/t_3e87766d_archie-renaux.jpg",
      "nombre": "Archie Renaux",
      "personaje": "Pedro"
    },
    {
      "img": "https://images.movieposterdb.com/profile_images/9657438/t_4f8d7491_david-jonsson.jpg",
      "nombre": "David Jonsson",
      "personaje": "Carlos"
    }
  ],
  "trailerId": "5nWH2Pd-x-c?playlist=5nWH2Pd-x-c&autoplay=1&iv_load_policy=3&loop=1&start="
},
{
  "_id": {
    "$oid": "66c8eb8f3b9fd081fe7cc8e8"
  },
  "titulo": "Deadpool and Wolverine",
  "genero": [
    "Sci-Fi",
    "Action",
    "Comedy"
  ],
  "duracion": 120,
  "sinopsis": " Wolverine se está recuperando de sus heridas cuando se cruza con el bocazas Deadpool. Ambos se unen para derrotar a un enemigo común.",
  "img": "https://posters.movieposterdb.com/24_04/2024/6263850/l_deadpool-wolverine-movie-poster_269f8e79.jpg",
  "casting": [
    {
      "img": "https://images.movieposterdb.com/profile_images/982/t_a3406fc1_josh-brolin.jpg",
      "nombre": "Josh Brolin",
      "personaje": "Cable"
    },
    {
      "img": "https://images.movieposterdb.com/profile_images/5351/t_9e9e1d79_ryan-reynolds.jpg",
      "nombre": "Ryan Reynolds",
      "personaje": "Wade Wilson"
    },
    {
      "img": "https://images.movieposterdb.com/profile_images/1072555/t_849ff8d1_morena-baccarin.jpg",
      "nombre": "Morena Baccarin",
      "personaje": "Vanessa"
    },
    {
      "img": "https://images.movieposterdb.com/profile_images/413168/t_264d9f39_hugh-jackman.jpg",
      "nombre": "Hugh Jackman",
      "personaje": "Logan"
    }
  ],
  "trailerId": "uDzfa0w86Vw?playlist=uDzfa0w86Vw&autoplay=1&iv_load_policy=3&loop=1&start="
},
{
  "_id": {
    "$oid": "66c8ec783b9fd081fe7cc8ea"
  },
  "titulo": "Mi villano favorito 4",
  "genero": [
    "Animation",
    "Adventure",
    "Comedy"
  ],
  "duracion": 120,
  "sinopsis": " Gru, Lucy, Margo, Edith y Agnes dan la bienvenida a un nuevo miembro a la familia, Gru Jr., que está decidido a atormentar a su padre. Gru se enfrenta a un nuevo enemigo, Maxime Le Mal y su novia Valentina, y la familia se ve obligada a huir.",
  "casting": [
    {
      "img": "https://images.movieposterdb.com/profile_images/136797/t_b97f0d53_steve-carell.jpg",
      "nombre": "Steve Carell",
      "personaje": "Gru"
    },
    {
      "img": "https://images.movieposterdb.com/profile_images/1325419/t_ed3f2fd3_kristen-wiig.jpg",
      "nombre": "Kristen Wiig",
      "personaje": "Lucy Wilde"
    },
    {
      "img": "https://images.movieposterdb.com/profile_images/1388927/t_4d99c01f_miranda-cosgrove.jpg",
      "nombre": "Miranda Cosgrove",
      "personaje": "Margo"
    }
  ],
  "img": "https://posters.movieposterdb.com/24_02/2024/7510222/l_despicable-me-4-movie-poster_3c4ff16e.jpg",
  "trailerId": "I0_qFoptZ4Y?playlist=I0_qFoptZ4Y&autoplay=1&iv_load_policy=3&loop=1&start="
},
{
  "_id": {
    "$oid": "66c8f2b03b9fd081fe7cc8f3"
  },
  "titulo": "Twister",
  "genero": [
    "Action",
    "Adventure",
    "Thriller"
  ],
  "duracion": 120,
  "sinopsis": "Una actualización de la película de 1996 'Twister', que se centró en un par de cazadores de tormentas que arriesgan sus vidas en un intento de probar un sistema de alerta meteorológica experimental.",
  "img": "https://posters.movieposterdb.com/24_02/2024/12584954/l_twisters-movie-poster_a76b8a6c.jpg",
  "casting": [
    {
      "img": "https://images.movieposterdb.com/profile_images/1412974/t_2b9c624e_glen-powell.jpg",
      "nombre": "Glen Powell",
      "personaje": "Tyler Owens"
    },
    {
      "img": "https://images.movieposterdb.com/profile_images/8402992/t_6c475bba_daisy-edgar-jones.jpg",
      "nombre": "Daisy Edgar-Jones",
      "personaje": "Kate Cooper"
    },
    {
      "img": "https://images.movieposterdb.com/profile_images/3297040/t_c7f6db4f_manini-gupta.jpg",
      "nombre": "Manini Gupta",
      "personaje": "Shanty"
    }
  ],
  "trailerId": "r-faf-bxqB8?playlist=r-faf-bxqB8&autoplay=1&iv_load_policy=3&loop=1&start="
},
{
  "_id": {
    "$oid": "66c8f6913b9fd081fe7cc8f5"
  },
  "titulo": "Harold y el crayon morado",
  "genero": [
    "Family",
    "Adventure",
    "Comedy"
  ],
  "duracion": 120,
  "sinopsis": " En su libro, el aventurero Harold puede hacer que cualquier cosa cobre vida con solo dibujarla. Cuando crece y se dibuja a si mismo fuera de las páginas del libro y entra en el mundo fisico, Harold descubre que tiene mucho que aprender sobre la vida real.",
  "img": "https://posters.movieposterdb.com/24_03/2023/1609486/l_harold-and-the-purple-crayon-movie-poster_0b6351d7.jpg",
  "casting": [
    {
      "img": "https://images.movieposterdb.com/profile_images/1382762/t_b127656b_elizabeth-becka.jpg",
      "nombre": "Elizabeth Becka",
      "personaje": "Sra. Barnaby"
    },
    {
      "img": "https://images.movieposterdb.com/profile_images/2179201/t_3d819a58_grace-junot.jpg",
      "nombre": "Gracia Junot",
      "personaje": "Yasmin"
    },
    {
      "img": "https://images.movieposterdb.com/profile_images/5372988/t_3aeb3183_catherine-davis.jpg",
      "nombre": "Catalina Davis",
      "personaje": "Kat"
    }
  ],
  "trailerId": "T4bvKwP870A?playlist=T4bvKwP870A&autoplay=1&iv_load_policy=3&loop=1&start="
},
{
  "_id": {
    "$oid": "66d506ee210ea2fc33469a3e"
  },
  "titulo": "The Crow",
  "genero": [
    "Action",
    "Crime",
    "Fantasy"
  ],
  "duracion": 120,
  "sinopsis": "Eric Draven y Shelly Webster son brutalmente asesinados cuando los demonios de su oscuro pasado les alcanzan. Ante la oportunidad de sacrificarse para salvar a su verdadero amor, Eric se propone vengarse despiadadamente de sus asesinos, atravesando el mundo de los vivos y los muertos para saldar sus deudas.",
  "img": "https://posters.movieposterdb.com/24_05/2024/1340094/l_the-crow-movie-poster_dc755402.jpg",
  "casting": [
    {
      "img": "https://images.movieposterdb.com/profile_images/803889/t_877f9ff4_bill-skarsgard.jpg",
      "nombre": "Bill Skarsgard",
      "personaje": "Eric Draven"
    },
    {
      "img": "https://images.movieposterdb.com/profile_images/12542507/t_d689842b_isabella-wei.jpg",
      "nombre": "Isabella Wei",
      "personaje": "Zadie"
    },
    {
      "img": "https://images.movieposterdb.com/profile_images/1983387/t_912957d9_david-bowles.jpg",
      "nombre": "David Bowles",
      "personaje": "Wickham"
    },
    {
      "img": "https://images.movieposterdb.com/profile_images/13070795/t_8f441361_paul-a-maynard.jpg",
      "nombre": "Paul A Maynard",
      "personaje": "Malcolm, Card Dealer"
    }
  ],
  "trailerId": "nuJsaUQ1GjE?playlist=nuJsaUQ1GjE&autoplay=1&iv_load_policy=3&loop=1&start="
},
{
  "_id": {
    "$oid": "66d5096c210ea2fc33469a3f"
  },
  "titulo": "Blink Twice",
  "genero": [
    "Mystery",
    "Thriller"
  ],
  "duracion": 120,
  "sinopsis": "Cuando el magnate de la tecnología Slater King conoce a la camarera Frida en su gala de recaudación de fondos, saltan chispas. Él la invita a acompañarle a él y a sus amigos a unas vacaciones de ensueño en su isla privada. Un auténtico paraíso. Las noches salvajes se mezclan con mañanas bañadas por el sol y todo el mundo se lo pasa en grande. Nadie quiere que el viaje termine, pero cuando empiezan a suceder cosas extrañas, Frida intuye que algo anda mal en ese lugar. Tendrá que descubrir la verdad si quiere salir viva de la fiesta.",
  "img": "https://posters.movieposterdb.com/24_08/2024/14858658/l_blink-twice-movie-poster_08399576.png",
  "casting": [
    {
      "img": "https://images.movieposterdb.com/profile_images/1475594/t_e859df65_channing-tatum.jpg",
      "nombre": "Channing Tatum",
      "personaje": "Slater King"
    },
    {
      "img": "https://images.movieposterdb.com/profile_images/5350/t_cac2d37b_simon-rex.jpg",
      "nombre": "Simon Rex",
      "personaje": "Cody"
    },
    {
      "img": "https://images.movieposterdb.com/profile_images/2630554/t_a9b34ab4_tiffany-persons.jpg",
      "nombre": "Tiffany Persons",
      "personaje": "Interviewer"
    },
    {
      "img": "https://images.movieposterdb.com/profile_images/385391/t_294843e1_aaron-himelstein.jpg",
      "nombre": "Aaron Himelstein",
      "personaje": "Asshole Manager"
    }
  ],
  "trailerId": "n58FlV79URs?playlist=n58FlV79URs&autoplay=1&iv_load_policy=3&loop=1&start="
}]